barcodejun/__init__.py
barcodejun/barcode.py
barcodejun/data.py
barcodejun/file_type.py
barcodejun/install.py
barcodejun/type.py
barcodejun/vers.py
barcodejun-1.0.1.dist-info/LICENSE
barcodejun-1.0.1.dist-info/METADATA
barcodejun-1.0.1.dist-info/WHEEL
barcodejun-1.0.1.dist-info/top_level.txt
barcodejun-1.0.1.dist-info/RECORD
