Metadata-Version: 2.1
Name: barcodejun
Version: 1.0.1
Summary: A barcode generator package
Author-email: ElevenTreeHole <ElevenTreeHole@gmail.com>
Project-URL: Homepage, https://github.com/ElevenTreeHole/barcodejun
Project-URL: Bug Tracker, https://github.com/ElevenTreeHole/barcodejun/issues
Classifier: Programming Language :: Python :: 3
Classifier: License :: OSI Approved :: MIT License
Classifier: Operating System :: OS Independent
Requires-Python: >=3.7
License-File: LICENSE
